rafcon-2.3.1.dist-info/METADATA
rafcon-2.3.1.dist-info/WHEEL
rafcon-2.3.1.dist-info/entry_points.txt
rafcon-2.3.1.dist-info/licenses/LICENSE.md
rafcon/.update-copyright.conf
rafcon/__init__.py
rafcon/__main__.py
rafcon/core/__init__.py
rafcon/core/config.py
rafcon/core/config.yaml
rafcon/core/constants.py
rafcon/core/custom_exceptions.py
rafcon/core/decorators.py
rafcon/core/default_script.py
rafcon/core/execution/__init__.py
rafcon/core/execution/base_execution_history.py
rafcon/core/execution/consumer_manager.py
rafcon/core/execution/consumers/__init__.py
rafcon/core/execution/consumers/abstract_execution_history_consumer.py
rafcon/core/execution/consumers/file_system_consumer.py
rafcon/core/execution/execution_engine.py
rafcon/core/execution/execution_history_factory.py
rafcon/core/execution/execution_history_items.py
rafcon/core/execution/execution_status.py
rafcon/core/execution/in_memory_execution_history.py
rafcon/core/global_variable_manager.py
rafcon/core/id_generator.py
rafcon/core/interface.py
rafcon/core/library_manager.py
rafcon/core/script.py
rafcon/core/singleton.py
rafcon/core/start.py
rafcon/core/state_elements/__init__.py
rafcon/core/state_elements/data_flow.py
rafcon/core/state_elements/data_port.py
rafcon/core/state_elements/logical_port.py
rafcon/core/state_elements/scope.py
rafcon/core/state_elements/state_element.py
rafcon/core/state_elements/transition.py
rafcon/core/state_machine.py
rafcon/core/state_machine_manager.py
rafcon/core/states/__init__.py
rafcon/core/states/barrier_concurrency_state.py
rafcon/core/states/concurrency_state.py
rafcon/core/states/container_state.py
rafcon/core/states/execution_state.py
rafcon/core/states/hierarchy_state.py
rafcon/core/states/library_state.py
rafcon/core/states/preemptive_concurrency_state.py
rafcon/core/states/state.py
rafcon/core/storage/__init__.py
rafcon/core/storage/storage.py
rafcon/design_patterns/__init__.py
rafcon/design_patterns/mvc/__init__.py
rafcon/design_patterns/mvc/controller.py
rafcon/design_patterns/mvc/model.py
rafcon/design_patterns/mvc/view.py
rafcon/design_patterns/observer/__init__.py
rafcon-2.3.1.dist-info/RECORD
