Metadata-Version: 2.1
Name: rafcon
Version: 2.3.1
Summary: Develop your robotic tasks with hierarchical state machines using an intuitive graphical user interface
Keywords: state machine,robotic,FSM,development,GUI,visual programming
Author-Email: Sebastian Brunner <sebastian.brunner@dlr.de>, Rico Belder <rico.belder@dlr.de>, Franz Steinmetz <franz.steinmetz@dlr.de>
License: EPL
Classifier: Development Status :: 4 - Beta
Classifier: Environment :: Console
Classifier: Environment :: X11 Applications :: GTK
Classifier: Framework :: Robot Framework
Classifier: Intended Audience :: Developers
Classifier: Intended Audience :: Education
Classifier: Intended Audience :: Manufacturing
Classifier: Intended Audience :: Science/Research
Classifier: License :: OSI Approved :: Eclipse Public License 1.0 (EPL-1.0)
Classifier: Natural Language :: English
Classifier: Operating System :: Unix
Classifier: Programming Language :: Python :: 3.6
Classifier: Topic :: Scientific/Engineering
Classifier: Topic :: Software Development
Classifier: Topic :: Utilities
Project-URL: Homepage, https://github.com/DLR-RM/RAFCON
Requires-Python: >=3.9
Requires-Dist: wrapt<2.0.0,>=1.14.0
Requires-Dist: astroid<4.0.0,>=2.15.8
Requires-Dist: gaphas<2.2.0,>=2.1.0
Requires-Dist: jsonconversion<2.0.0,>=1.1.0
Requires-Dist: psutil<6.0.0,>=5.0.0
Requires-Dist: pycairo<2.0.0,>=1.11.0
Requires-Dist: pylint<4.0.0,>=2.11.0
Requires-Dist: simplegeneric<1.0.0,>=0.5.0
Requires-Dist: numpy<3.0,>=1.23
Requires-Dist: pandas<2.0.0,>=1.2.0
Requires-Dist: yaml_configuration<0.4.0,>=0.2.5
Requires-Dist: PyGObject<3.51.0,>=3.42.0
Requires-Dist: packaging>=21
Requires-Dist: setuptools; python_version >= "3.12"
